DESCRIPTION.rst
MANIFEST.in
setup.py
maasutil/__init__.py
maasutil/maasutil.py
maasutil.egg-info/PKG-INFO
maasutil.egg-info/SOURCES.txt
maasutil.egg-info/dependency_links.txt
maasutil.egg-info/entry_points.txt
maasutil.egg-info/top_level.txt