Metadata-Version: 1.1
Name: maasutil
Version: 0.0.5
Summary: A utility for command line MaaS interrogation
Home-page: https://github.com/lgfausak/maasutil
Author: Greg Fausak
Author-email: greg@tacodata.com
License: Apache Software License
Keywords: kubernetes k8s development kube-version-change cat
Platform: UNKNOWN
Classifier: Development Status :: 3 - Alpha
Classifier: Intended Audience :: Developers
Classifier: Topic :: Software Development :: Build Tools
Classifier: License :: OSI Approved :: Apache Software License
Classifier: Programming Language :: Python :: 2
Classifier: Programming Language :: Python :: 2.6
Classifier: Programming Language :: Python :: 2.7
Classifier: Programming Language :: Python :: 3
Classifier: Programming Language :: Python :: 3.2
Classifier: Programming Language :: Python :: 3.3
Classifier: Programming Language :: Python :: 3.4
